parsita/__init__.py
parsita/metaclasses.py
parsita/options.py
parsita/parsers/__init__.py
parsita/parsers/_alternative.py
parsita/parsers/_any.py
parsita/parsers/_base.py
parsita/parsers/_conversion.py
parsita/parsers/_debug.py
parsita/parsers/_end_of_source.py
parsita/parsers/_literal.py
parsita/parsers/_optional.py
parsita/parsers/_predicate.py
parsita/parsers/_regex.py
parsita/parsers/_repeated.py
parsita/parsers/_repeated_seperated.py
parsita/parsers/_sequential.py
parsita/parsers/_success.py
parsita/parsers/_until.py
parsita/py.typed
parsita/state/__init__.py
parsita/state/_exceptions.py
parsita/state/_reader.py
parsita/state/_result.py
parsita/state/_state.py
parsita/util.py
parsita-2.2.4.dist-info/licenses/LICENSE
parsita-2.2.4.dist-info/WHEEL
parsita-2.2.4.dist-info/METADATA
parsita-2.2.4.dist-info/RECORD
