Metadata-Version: 2.4
Name: parsita
Version: 2.2.4
Summary: Parser combinator library for Python
Keywords: text,parsing,parser,combinator
Author: David Hagen
Author-email: David Hagen <david@drhagen.com>
License-Expression: MIT
License-File: LICENSE
Classifier: Development Status :: 5 - Production/Stable
Classifier: Intended Audience :: Developers
Classifier: License :: OSI Approved :: MIT License
Classifier: Operating System :: OS Independent
Classifier: Programming Language :: Python :: 3
Classifier: Programming Language :: Python :: 3.10
Classifier: Programming Language :: Python :: 3.11
Classifier: Programming Language :: Python :: 3.12
Classifier: Programming Language :: Python :: 3.13
Classifier: Programming Language :: Python :: 3.14
Classifier: Topic :: Software Development :: Libraries :: Python Modules
Requires-Dist: returns>=0.20,<0.27
Requires-Python: >=3.10
Project-URL: Documentation, https://parsita.drhagen.com
Project-URL: Repository, https://github.com/drhagen/parsita
